MANIFEST.in
README.md
setup.py
dbt/adapters/spark/__init__.py
dbt/adapters/spark/__version__.py
dbt/adapters/spark/column.py
dbt/adapters/spark/connections.py
dbt/adapters/spark/impl.py
dbt/adapters/spark/python_submissions.py
dbt/adapters/spark/relation.py
dbt/adapters/spark/session.py
dbt/include/spark/__init__.py
dbt/include/spark/dbt_project.yml
dbt/include/spark/profile_template.yml
dbt/include/spark/macros/adapters.sql
dbt/include/spark/macros/apply_grants.sql
dbt/include/spark/macros/materializations/clone.sql
dbt/include/spark/macros/materializations/seed.sql
dbt/include/spark/macros/materializations/snapshot.sql
dbt/include/spark/macros/materializations/table.sql
dbt/include/spark/macros/materializations/view.sql
dbt/include/spark/macros/materializations/incremental/column_helpers.sql
dbt/include/spark/macros/materializations/incremental/incremental.sql
dbt/include/spark/macros/materializations/incremental/strategies.sql
dbt/include/spark/macros/materializations/incremental/validate.sql
dbt/include/spark/macros/utils/any_value.sql
dbt/include/spark/macros/utils/array_append.sql
dbt/include/spark/macros/utils/array_concat.sql
dbt/include/spark/macros/utils/array_construct.sql
dbt/include/spark/macros/utils/assert_not_null.sql
dbt/include/spark/macros/utils/bool_or.sql
dbt/include/spark/macros/utils/concat.sql
dbt/include/spark/macros/utils/dateadd.sql
dbt/include/spark/macros/utils/datediff.sql
dbt/include/spark/macros/utils/escape_single_quotes.sql
dbt/include/spark/macros/utils/listagg.sql
dbt/include/spark/macros/utils/safe_cast.sql
dbt/include/spark/macros/utils/split_part.sql
dbt/include/spark/macros/utils/timestamps.sql
dbt_spark_klook_data.egg-info/PKG-INFO
dbt_spark_klook_data.egg-info/SOURCES.txt
dbt_spark_klook_data.egg-info/dependency_links.txt
dbt_spark_klook_data.egg-info/not-zip-safe
dbt_spark_klook_data.egg-info/requires.txt
dbt_spark_klook_data.egg-info/top_level.txt