Metadata-Version: 2.1
Name: dbt-spark-klook-data
Version: 1.8.2
Summary: The Apache Spark adapter plugin for dbt
Home-page: https://github.com/dbt-labs/dbt-spark
Author: dbt Labs, cyril lu
Author-email: info@dbtlabs.com,cyril.lu@klook.com
Classifier: Development Status :: 5 - Production/Stable
Classifier: License :: OSI Approved :: Apache Software License
Classifier: Operating System :: Microsoft :: Windows
Classifier: Operating System :: MacOS :: MacOS X
Classifier: Operating System :: POSIX :: Linux
Classifier: Programming Language :: Python :: 3.8
Classifier: Programming Language :: Python :: 3.9
Classifier: Programming Language :: Python :: 3.10
Classifier: Programming Language :: Python :: 3.11
Requires-Python: >=3.8
Provides-Extra: ODBC
Provides-Extra: PyHive
Provides-Extra: session
Provides-Extra: all
